HW_Solution/HW1/alu.v
module alu
    // Declaring inputs & outputs
    (output reg zero, //1bit
    output reg [31:0] result, //32bit
    input wire [31:0] op1, //32bit
    input wire [31:0] op2, //32bit
    input wire [3:0] alu_op); //4bit
    
    //Parameters of alu_op -- MUX!!!
    parameter[3:0] ALUOP_AND = 4'b0000;
    parameter[3:0] ALUOP_OR = 4'b0001;
    parameter[3:0] ALUOP_ADD = 4'b0010;
    parameter[3:0] ALUOP_SUB = 4'b0110;
    parameter[3:0] ALUOP_SLT = 4'b0111; //less than
    parameter[3:0] ALUOP_SRL = 4'b1000; //right shift
    parameter[3:0] ALUOP_SLL = 4'b1001; //left shift
    parameter[3:0] ALUOP_SRA = 4'b1010; //right arithmetic shift
    parameter[3:0] ALUOP_XOR = 4'b1101;


    always@(*) //κατά τον εντοπισμό αλλαγών στις εισόδους.
        begin
            case (alu_op)
                ALUOP_AND: result = op1 & op2;
                ALUOP_OR: result = op1 | op2;
                ALUOP_ADD: result = op1 + op2;
                ALUOP_SUB: result = op1 - op2;
                ALUOP_SLT: result = ($signed(op1) < $signed(op2)) ? 32'b1 : 32'b0; //Προσημασμένη Σύγκριση! 
                //1 αν ειναι ισχύει η σύγκριση, 0 αν δεν ισχυει
                ALUOP_SRL: result = op1 >> op2[4:0];
                ALUOP_SLL: result = op1 << op2[4:0];
                ALUOP_SRA: result = $unsigned($signed(op1) >>> op2[4:0]);
                //η τιμή που ολισθαίνει --> μετατροπή σε προσημασμένο αριθμό  
                //το αποτέλεσμα --> μετατροπή σε μη προσημασμένο αριθμό
                ALUOP_XOR: result = op1 ^ op2;
                default: result = 32'b0; 
            endcase

            zero = (result == 32'b0) ? 1'b1 : 1'b0;
        end
             
endmodule

/*
alu_op Πράξη Αποτέλεσμα
0000 Λογική AND     op1 & op2
0001 Λογική OR      op1 | op2
0010 Πρόσθεση       op1 + op2
0110 Αφαίρεση       op1 - op2
0111 Μικρότερο από  op1 < op2 
1000 Λογική ολίσθηση δεξιά κατά op2 bits    op1 >> op2[4:0]
1001 Λογική ολίσθηση αριστερά κατά op2 bits     op1 << op2[4:0]
1010 Αριθμητική ολίσθηση δεξιά κατά op2 bits    op1 >>> op2[4:0]
1101 Λογική XOR     op1 ^ op2
*/

HW_Solution/HW2/decoder.v
//grammi 4 !!!

module decoder
    (output [3:0] alu_op,// reg if always block
    input btnr, btnl, btnc); //4bit
    
    //internal nets
    wire x1,x2,x3,x4;
    wire y1,y2,y3,y4;
    wire z1,z2,z3,z4;
    wire r1,r2,r3,r4;

 //gate: (output, inputs) --> STRUCTURAL VERILOG
    //alu_op[0]: 
    not(x1, btnr);
    and(x2, x1, btnl);
    xor(x3, btnl, btnc);
    and(x4, btnr, x3);
    or (alu_op[0], x2, x4);

    //alu_op[1]:
    not(y2, btnl);
    not(y3, btnc);
    and(y1, btnr, btnl);
    and(y4, y2, y3);
    or(alu_op[1], y1, y4);
        
    //alu_op[2]:  
    not(z1, btnc);
    and(z2, btnr, btnl);
    xor(z3, btnr, btnl);
    or (z4, z2, z3);
    and(alu_op[2], z1, z4);

    //alu_op[3]: 
    not(r1, btnr);
    xnor(r2, btnr, btnc);
    and(r3, r1, btnc);
    or(r4, r3, r2);
    and(alu_op[3], r4, btnl);

endmodule

/*
Το σήμα 'alu_op' καθορίζει ποια πράξη της ALU θα εκτελεστεί. Θα καθορίσετε ποια λειτουργία θα
εκτελέσετε με βάση την τιμή των τριών πλήκτρων: btnl, btnc και btnr. Θα πρέπει να
δημιουργήσετε το συνδυαστικό κύκλωμα των Σχημάτων 2-5 που να παράγει το κατάλληλο σήμα
'alu_op' με βάση την τιμή αυτών των τριών πλήκτρων. Υλοποιήστε το κύκλωμα decoder.v σε
structural verilog και συνδέστε το στο κύκλωμα αριθμομηχανής calc.v
*/

HW_Solution/HW2/calc.v
`include "alu.v"
`include "decoder.v"

module calc 
    (output wire [15:0] led, //16bit LED για την έξοδο του συσσωρευτή
    input clk, btnc, btnl, btnu, btnr, btnd, //1bit 
    input [15:0] sw); //16bit Διακόπτες για την εισαγωγή δεδομένων
    
    //Internal nets
    reg [15:0] accumulator; //16bit -- reg_out of a register
    // Σήματα για σύνδεση με την ALU
    wire [31:0] alu_op1;
    wire [31:0] alu_op2;
    wire [31:0] alu_result;
    wire [3:0] alu_op;


    always @(posedge clk) //sensitivity list --> μόνο clk, το reset είναι σύγχρονο σήμα
        begin : ACCUMULATOR
            //ACCUMULATOR 16bit
            if (btnu) //reset accumulator - σύγχρονα!!
                accumulator <= 16'b0;
            else if (btnd) begin //enable --> να ενημερώνεται κάθε φορά που πατιέται το "down" (btnd)
                    accumulator <= alu_result[15:0];
                    //τα 16 χαμηλότερα bit της εξόδου "result" 32 bit της ALU.
            end   
            
        end

    // Σύνδεση των εξόδων LED με τον accumulator
    assign led = accumulator; 

    //Επέκταση προσήμων
    assign alu_op1 = { {16{accumulator[15]}} ,accumulator};
     //● 'op1' της ALU. --> σήμα 32-bit (επέκταση προσήμου) του accumulator 16-bit.     
    assign alu_op2 = { {16{sw[15]}} ,sw};
     //● 'op2' της ALU --> σήμα 32-bit (επέκταση προσήμου) των εισόδων του διακόπτη 16-bit.

    //Instantiation of Internal Modules
    decoder calc_aluop (.alu_op(alu_op) ,.btnr(btnr) ,.btnl(btnl) ,.btnc(btnc)); //παίρνω την alu_op από εδώ
    alu calc_alu(.result(alu_result) ,.op1(alu_op1) ,.op2(alu_op2) ,.alu_op(alu_op));

endmodule

HW_Solution/HW2/calc_tb.v
`timescale 1ns/1ps //δήλωση χρόνου καθυστερήσεων
`include "calc.v"

module calc_tb;

    // Inputs
    reg clk;
    reg btnc, btnl, btnu, btnr, btnd;
    reg [15:0] sw;
    // Outputs
    wire [15:0] led;

    //Instantiation of calc module
    calc TB (.led(led),.clk(clk),.btnc(btnc),.btnl(btnl),.btnu(btnu),.btnr(btnr),.btnd(btnd),.sw(sw));

    initial
    begin
        clk = 1'b1;
    end
    always
    begin
        #10 clk = ~clk; //παλμός ρολογιού
    end

    initial begin 
        //Δημιουργία αρχείου vcd για να τρέξω την κυματομορφή του αρχείου
        $dumpfile("calc_tb.vcd"); //value change dump
        $dumpvars(0,calc_tb);

        btnd = 1'b1; //btnd --> enable of accumulator
        
        //Reset
        btnu = 1'b1; //btnu --> reset
        #10;
        #10 btnu = 1'b0; 
        #10;

        //OR 
        #10 btnl=1'b0; btnc=1'b1; btnr=1'b1; sw = 16'h1234;
        #10;
        
        //AND - 3'b010 & sw==16'h0ff0
        #10 btnl=1'b0; btnc=1'b1; btnr=1'b0; sw = 16'h0ff0;
        #10;

        //ADD - 3'b000 & sw==16'h324f
        #10 btnl=1'b0; btnc=1'b0; btnr=1'b0; sw = 16'h324f;
        #10;

        //SUB - 3'b001 & sw==16'h2d31
        #10 btnl=1'b0; btnc=1'b0; btnr=1'b1; sw = 16'h2d31;
        #10;

        //XOR - 3'b100 & sw==16'hffff
        #10 btnl=1'b1; btnc=1'b0; btnr=1'b0; sw = 16'hffff;
        #10;

        //Less than - 3'b101 & sw==16'h7346
        #10 btnl=1'b1; btnc=1'b0; btnr=1'b1; sw = 16'h7346;
        #10;

        //Shift Left Logical - 3'b110 & sw==16'h0004
        #10 btnl=1'b1; btnc=1'b1; btnr=1'b0; sw = 16'h0004;
        #10;

        //Shift Right Arithmetic - 3'b111 & sw==16'h0004
        #10 btnl=1'b1; btnc=1'b1; btnr=1'b1; sw = 16'h0004;
        #10;

        //Less than - 3'b101 & sw==16'hffff
        #10 btnl=1'b1; btnc=1'b0; btnr=1'b1; sw = 16'hffff;
        #10;

        #10 $finish;//πρόγραμμα προσομοίωσης πρέπει να σταματήσει
    end

endmodule

/*
Τestbench
Δημιουργήστε ένα testbench το οποίο θα ελέγχει την ορθή λειτουργία της αριθμομηχανής, καθώς
και την ορθή λειτουργία της ALU. Ελέγξτε την αριθμομηχανή με τη σειρά για τις τιμές:
-btnl, btnc, btnr (input) 
-Previous value (acc.)
-Switches (input)
-Function in ALU
-Expected Result

(btnu for reset) xxxx xxxx Reset 0x0
0,1,1 0x0 0x1234 OR 0x1234
0,1,0 0x1234 0x0ff0 AND 0x0230
0,0,0 0x0230 0x324f ADD 0X347f
0,0,1 0x347f 0x2d31 SUB 0x074e
1,0,0 0x074e 0xffff XOR 0xf8b1
1,0,1 0xf8b1 0x7346 Less Than 0x0001
1,1,0 0x0001 0x0004 Shift Left Logical 0x0010
1,1,1 0x0010 0x0004 Shift Right Arithmetic 0x0001
1,0,1 0x0001 0xffff Less Than 0x0000

*/

HW_Solution/HW2/calc_tb.vcd
$date
	Sun Jan 21 18:10:38 2024
$end
$version
	Icarus Verilog
$end
$timescale
	1ps
$end
$scope module calc_tb $end
$var wire 16 ! led [15:0] $end
$var reg 1 " btnc $end
$var reg 1 # btnd $end
$var reg 1 $ btnl $end
$var reg 1 % btnr $end
$var reg 1 & btnu $end
$var reg 1 ' clk $end
$var reg 16 ( sw [15:0] $end
$scope module TB $end
$var wire 4 ) alu_op [3:0] $end
$var wire 32 * alu_op1 [31:0] $end
$var wire 32 + alu_op2 [31:0] $end
$var wire 32 , alu_result [31:0] $end
$var wire 1 - btnc $end
$var wire 1 . btnd $end
$var wire 1 / btnl $end
$var wire 1 0 btnr $end
$var wire 1 1 btnu $end
$var wire 1 2 clk $end
$var wire 16 3 led [15:0] $end
$var wire 16 4 sw [15:0] $end
$var reg 16 5 accumulator [15:0] $end
$scope module calc_aluop $end
$var wire 4 6 alu_op [3:0] $end
$var wire 1 - btnc $end
$var wire 1 / btnl $end
$var wire 1 0 btnr $end
$var wire 1 7 r1 $end
$var wire 1 8 r2 $end
$var wire 1 9 r3 $end
$var wire 1 : r4 $end
$var wire 1 ; x1 $end
$var wire 1 < x2 $end
$var wire 1 = x3 $end
$var wire 1 > x4 $end
$var wire 1 ? y1 $end
$var wire 1 @ y2 $end
$var wire 1 A y3 $end
$var wire 1 B y4 $end
$var wire 1 C z1 $end
$var wire 1 D z2 $end
$var wire 1 E z3 $end
$var wire 1 F z4 $end
$upscope $end
$scope module calc_alu $end
$var wire 4 G alu_op [3:0] $end
$var wire 32 H op1 [31:0] $end
$var wire 32 I op2 [31:0] $end
$var reg 32 J result [31:0] $end
$var reg 1 K zero $end
$upscope $end
$scope begin ACCUMULATOR $end
$upscope $end
$upscope $end
$upscope $end
$enddefinitions $end
#0
$dumpvars
1K
b0 J
bx I
b0 H
bx G
xF
xE
xD
xC
xB
xA
x@
x?
x>
x=
x<
x;
x:
x9
x8
x7
bx 6
b0 5
bx 4
b0 3
12
11
x0
x/
1.
x-
b0 ,
bx +
b0 *
bx )
bx (
1'
1&
x%
x$
1#
x"
b0 !
$end
#10000
0'
02
#20000
0&
01
1'
12
#30000
0'
02
#40000
0K
b1001000110100 J
b1001000110100 ,
09
1:
0B
1F
0;
1>
07
0A
0C
18
0<
1=
1@
0?
0D
1E
b1 )
b1 6
b1 G
b1001000110100 (
b1001000110100 4
b1001000110100 +
b1001000110100 I
1%
10
1"
1-
0$
0/
1'
12
#50000
0'
02
#60000
b1001000110100 5
b1001000110100 *
b1001000110100 H
b1001000110100 !
b1001000110100 3
0K
b0 )
b0 6
b0 G
0F
19
1:
b1000110000 J
b1000110000 ,
1;
0>
0E
17
08
b111111110000 (
b111111110000 4
b111111110000 +
b111111110000 I
0%
00
1'
12
#70000
0'
02
#80000
b1000110000 5
b1000110000 *
b1000110000 H
b1000110000 !
b1000110000 3
b10 )
b10 6
b10 G
1B
b11010001111111 J
b11010001111111 ,
0=
1A
1C
18
09
b11001001001111 (
b11001001001111 4
b11001001001111 +
b11001001001111 I
0"
0-
1'
12
#90000
0'
02
#100000
b11010001111111 5
b11010001111111 *
b11010001111111 H
b11010001111111 !
b11010001111111 3
b110 )
b110 6
b110 G
1F
0:
b11101001110 J
b11101001110 ,
0;
1E
07
08
b10110100110001 (
b10110100110001 4
b10110100110001 +
b10110100110001 I
1%
10
1'
12
#110000
0'
02
#120000
b11101001110 5
b11101001110 *
b11101001110 H
b11101001110 !
b11101001110 3
b1101 )
b1101 6
b1101 G
1<
1:
0B
b11111111111111111111100010110001 J
b11111111111111111111100010110001 ,
1;
17
18
1=
0@
b1111111111111111 (
b1111111111111111 4
b11111111111111111111111111111111 +
b11111111111111111111111111111111 I
0%
00
1$
1/
1'
12
#130000
0'
02
#140000
b1111100010110001 5
b11111111111111111111100010110001 *
b11111111111111111111100010110001 H
b1111100010110001 !
b1111100010110001 3
0K
0<
b111 )
b111 6
b111 G
0:
b1 J
b1 ,
0;
1>
1?
1D
0E
07
08
b111001101000110 (
b111001101000110 4
b111001101000110 +
b111001101000110 I
1%
10
1'
12
#150000
0'
02
#160000
b1 5
b1 *
b1 H
b1 !
b1 3
1:
0K
b10000 J
b10000 ,
1<
19
b1001 )
b1001 6
b1001 G
1;
0>
0?
0D
1E
17
0=
0A
0C
b100 (
b100 4
b100 +
b100 I
0%
00
1"
1-
1'
12
#170000
0'
02
#180000
b10000 5
b10000 *
b10000 H
b10000 !
b10000 3
0K
b1 J
b1 ,
0<
b1010 )
b1010 6
b1010 G
09
0;
1?
1D
0E
07
18
1%
10
1'
12
#190000
0'
02
#200000
b1 5
b1 *
b1 H
b1 !
b1 3
1>
b111 )
b111 6
b111 G
0:
1K
b0 J
b0 ,
1=
1A
1C
08
b1111111111111111 (
b1111111111111111 4
b11111111111111111111111111111111 +
b11111111111111111111111111111111 I
0"
0-
1'
12
#210000
0'
02
#220000
b0 5
b0 *
b0 H
b0 !
b0 3
1'
12
