HW_Solution/HW5/ram.v
module DATA_MEMORY(
input clk,
input we,
input [8:0] addr,
input [31:0] din,
output reg [31:0] dout
);

reg [31:0] RAM [511:0];

always @(posedge clk)
begin
    if(we)
        RAM[addr] = din;
    else
        dout = RAM[addr];
end

endmodule

HW_Solution/HW5/rom.v
module INSTRUCTION_MEMORY(
 input clk,
 input [8:0] addr,
 output reg [31:0] dout
 );
 
reg [7:0] ROM [511:0];

initial
begin
    $readmemb("rom_bytes.data", ROM);
end

always @(posedge clk)
begin
    dout <= {ROM[addr], ROM[addr + 1], ROM[addr + 2], ROM[addr + 3]};
end

endmodule

HW_Solution/HW1/alu.v
module alu
    // Declaring inputs & outputs
    (output reg zero, //1bit
    output reg [31:0] result, //32bit
    input wire [31:0] op1, //32bit
    input wire [31:0] op2, //32bit
    input wire [3:0] alu_op); //4bit
    
    //Parameters of alu_op -- MUX!!!
    parameter[3:0] ALUOP_AND = 4'b0000;
    parameter[3:0] ALUOP_OR = 4'b0001;
    parameter[3:0] ALUOP_ADD = 4'b0010;
    parameter[3:0] ALUOP_SUB = 4'b0110;
    parameter[3:0] ALUOP_SLT = 4'b0111; //less than
    parameter[3:0] ALUOP_SRL = 4'b1000; //right shift
    parameter[3:0] ALUOP_SLL = 4'b1001; //left shift
    parameter[3:0] ALUOP_SRA = 4'b1010; //right arithmetic shift
    parameter[3:0] ALUOP_XOR = 4'b1101;


    always@(*) //κατά τον εντοπισμό αλλαγών στις εισόδους.
        begin
            case (alu_op)
                ALUOP_AND: result = op1 & op2;
                ALUOP_OR: result = op1 | op2;
                ALUOP_ADD: result = op1 + op2;
                ALUOP_SUB: result = op1 - op2;
                ALUOP_SLT: result = ($signed(op1) < $signed(op2)) ? 32'b1 : 32'b0; //Προσημασμένη Σύγκριση! 
                //1 αν ειναι ισχύει η σύγκριση, 0 αν δεν ισχυει
                ALUOP_SRL: result = op1 >> op2[4:0];
                ALUOP_SLL: result = op1 << op2[4:0];
                ALUOP_SRA: result = $unsigned($signed(op1) >>> op2[4:0]);
                //η τιμή που ολισθαίνει --> μετατροπή σε προσημασμένο αριθμό  
                //το αποτέλεσμα --> μετατροπή σε μη προσημασμένο αριθμό
                ALUOP_XOR: result = op1 ^ op2;
                default: result = 32'b0; 
            endcase

            zero = (result == 32'b0) ? 1'b1 : 1'b0;
        end
             
endmodule

/*
alu_op Πράξη Αποτέλεσμα
0000 Λογική AND     op1 & op2
0001 Λογική OR      op1 | op2
0010 Πρόσθεση       op1 + op2
0110 Αφαίρεση       op1 - op2
0111 Μικρότερο από  op1 < op2 
1000 Λογική ολίσθηση δεξιά κατά op2 bits    op1 >> op2[4:0]
1001 Λογική ολίσθηση αριστερά κατά op2 bits     op1 << op2[4:0]
1010 Αριθμητική ολίσθηση δεξιά κατά op2 bits    op1 >>> op2[4:0]
1101 Λογική XOR     op1 ^ op2
*/

HW_Solution/HW3/regfile.v
/*αρχείο καταχωρητών
Σχεδόν όλες οι εντολές διαβάζουν ή/και γράφουν στο αρχείο καταχωρητών.
*/
module regfile
    (input clk, 
    input write, //1bit -- Σήμα ελέγχου που υποδεικνύει εγγραφή
    input [4:0] readReg1, readReg2, //-- Διεύθυνση για τη θύρα ανάγνωσης 1 & 2
    input [4:0] writeReg, // -- Διεύθυνση για θύρα εγγραφής
    input [31:0] writeData, //32bit -- Δεδομένα προς εγγραφή
    output reg [31:0] readData1, readData2); //32bit -- Δεδομένα ανάγνωσης από τη θύρα 1 & 2
    
    //32×32-bit αρχείο καταχωρητών
    reg [31:0] registers [0:31]; //array of 32 registers, 32 bit vectors
    integer i;

//Αρχικοποιήστε τους 32 καταχωρητές με μηδενικά μέσω ενός initial block και μιας for.
    initial begin // Initialize Registers 32x32bit
        for (i=0; i<32; i=i+1) 
            registers[i] = 32'b0;
    end
    
    always @(posedge clk) 
    begin
        //Διαβάστε τις τιμές των καταχωρητών ΓΙΑ κάθε έξοδο (readData1, readData2) 
        readData1 <= registers[readReg1];
        readData2 <= registers[readReg2];

        // εγγράψτε τα δεδομένα από το writeData στην αντίστοιχη διεύθυνση που έχετε ως είσοδο.
        if (write) 
        begin 
            registers[writeReg] <= writeData;
        
        // Προσέξτε την περίπτωση που η διεύθυνση εγγραφής == με κάποια από τις διευθύνσεις ανάγνωσης.

            if (writeReg == readReg1) //readReg1 --> Διεύθυνση για τη θύρα ανάγνωσης 1
                readData1 <= writeData;
                //readData1 --> Δεδομένα ανάγνωσης από τη θύρα 1 
            if (writeReg == readReg2) 
                readData2  <= writeData;
        end
    end
endmodule
/* 
Ύστερα μέσω ενός always block διαβάστε τις τιμές των καταχωρητών από κάθε έξοδο (readData1, readData2) 
και ανάλογα με το σήμα write εγγράψτε τα δεδομένα από το writeData στην αντίστοιχη διεύθυνση που έχετε ως είσοδο. 
Προσέξτε την περίπτωση που η διεύθυνση εγγραφής είναι ίδια με κάποια από τις διευθύνσεις ανάγνωσης. */

/* 
clk Είσοδος 1 Ρολόι
readReg1 Είσοδος 5 Διεύθυνση για τη θύρα ανάγνωσης 1
readReg2 Είσοδος 5 Διεύθυνση για τη θύρα ανάγνωσης 2
writeReg Είσοδος 5 Διεύθυνση για θύρα εγγραφής
writeData Είσοδος 32 Δεδομένα προς εγγραφή
write Είσοδος 1 Σήμα ελέγχου που υποδεικνύει εγγραφή
readData1 Έξοδος 32 Δεδομένα ανάγνωσης από τη θύρα 1
readData2 Έξοδος 32 Δεδομένα ανάγνωσης από τη θύρα 2
*/

HW_Solution/HW4/datapath.v
`include "alu.v"
`include "regfile.v"

module datapath
    //Inputs
    (input clk, //clock 
    input rst, //Σύγχρονο reset
    input [31:0] instr, // Δεδομένα εντολών από τη μνήμη εντολών
    input PCSrc, // Πηγή του PC
    input ALUSrc, //Πηγή του 2ου τελεστή της ALU
    input RegWrite, //Εγγραφή δεδομένων στους καταχωρητές
    input MemToReg,  //Πολυπλέκτης εισόδου στους καταχωρητές
    input [3:0] ALUCtrl,//Δείχνει ποια λειτουργία πρέπει να εκτελέσει η ALU
    input loadPC, //Ενημέρωση του PC με μια νέα τιμή
    input [31:0] dReadData, //Δεδομένα προς ανάγνωση από τη μνήμη δεδομένων
    //Outputs
    output [31:0] dAddress, // Διεύθυνση για δεδομένα μνήμης
    output [31:0] dWriteData, // Δεδομένα προς εγγραφή στη μνήμη δεδομένων
    output reg [31:0] PC, //Program Counter
    output Zero,  //Ένδειξη μηδενισμού ALU
    output [31:0] WriteBackData); //WriteBack δεδομένα που επιστρέφουν στους καταχωρητές


    parameter [31:0] INITIAL_PC = 32'h00400000;
            //Parameters of Instruction Types
    parameter [6:0] OP_I = 7'b0010011; //I-type
    parameter [6:0] OP_LW = 7'b0000011; //LW
    parameter [6:0] OP_SW = 7'b0100011; //SW
    parameter [6:0] OP_BEQ = 7'b1100011; //BEQ
    parameter [6:0] OP_R = 7'b0110011; //R-type

    //INTERNAL NETS--------------------------------------------------------------------------------
    //Regfile
    wire [31:0] readData1;
    wire [31:0] readData2;
    reg [31:0] writeData; // ram.v ---> MUX WRITEBACK ---> regfile.writeData
    //ALU
    wire [31:0] alu_result;
    reg [31:0] alu_op2; // --> MUX ALU_OP2 ---> alu.alu_op2
    //PC
    wire [31:0] branch_offset;
    //Immune Generation
    wire [6:0] opcode;
    reg [31:0] immI, immS, immB, immLW; //επέκταση προσήμου


    //Instantiation----------------------------------------------------------------------------------
    regfile datapath__REGFILE(.clk(clk) ,.write(RegWrite) ,.readReg1(instr[19:15]), .readReg2(instr[24:20]) ,.writeReg(instr[11:7]) 
                            ,.writeData(writeData) ,.readData1(readData1) ,.readData2(readData2));
    alu datapath_ALU(.zero(Zero) ,.result(alu_result) ,.op1(readData1) ,.op2(alu_op2) , .alu_op(ALUCtrl));  

    assign dAddress = alu_result; //από Σχήμα 6 και Σχημα 7
    assign dWriteData = readData2; //από Σχήμα 7

    //MUX WRITEBACK 
    always @* 
    begin 
        writeData = (MemToReg) ? (dReadData) : dAddress ; 
    end
    
    assign WriteBackData = writeData;  //Τα δεδομένα που γράφονται στους καταχωρητές πρέπει επίσης να συνδεθούν στην έξοδο WriteBackData
    

    //MUX ALU_OP2 ---> (ALUSrc)
    always @*
    begin
        case(opcode) //από immediate Generation
            OP_I: alu_op2 = (ALUSrc) ? immI : readData2; //I-type - ALU Immediate
            OP_SW: alu_op2 = (ALUSrc) ? immS : readData2; //S-type - SW - store
            OP_LW: alu_op2 = (ALUSrc) ? immLW : readData2; //LW - load
            OP_BEQ: alu_op2 = (ALUSrc) ? immB : readData2; //B-type (BEQ) διακλάδωση
        endcase
    end      


// --------------------------------------------------------------PC----------------------------------------------------------------
    assign branch_offset = (immB << 1); //SLL  (????)

    always @(posedge clk)  //(rst είναι σύγχρονο!)
    begin //Program Counter - PC 
        if (rst)
            PC <= INITIAL_PC;
        else begin
            if (loadPC) //enable
            begin // MUX PC  --> (PSCrc)
                PC = (PCSrc) ? (PC + branch_offset) : (PC + 32'd4) ;//branch_offset μόνο για B-type(διακλαδωση) (decimal4)
            end
        end
    end

//----------------------------------------------------IMMEDIATE GENERATION---------------------------------------------------------------
    assign opcode = instr[6:0];

    always @*
    begin //Immediate Generation
        case(opcode)
            OP_I: immI = { {20{instr[31]}} , instr[31:20]}; //I-type
            OP_SW: immS = { {20{instr[31]}}, instr[31:25], instr[11:7]}; //S-type - SW
            OP_LW: immLW = { {20{instr[31]}} , instr[31:20]}; //LW
            OP_BEQ: immB = { {20{instr[31]}}, instr[31], instr[7], instr[30:25], instr[11:8] }; //B-type (BEQ)
        endcase
    end


endmodule

//ΛΑΘΟΣ Δεν εχω παρει την περιπτωση του R για immR, οποτε λάθος και στο ALUSrc

HW_Solution/HW5/multicycle.v
`include "datapath.v"
//`include "ram.v"
//`include "rom.v"

module multicycle
    (input clk, //clock 
    input rst, //Σύγχρονο reset
    input [31:0] instr, // Δεδομένα εντολών από τη μνήμη εντολών
    input [31:0] dReadData, //Δεδομένα προς ανάγνωση από τη μνήμη δεδομένων
    output [31:0] PC, //Program Counter
    output [31:0] dAddress, // Διεύθυνση για δεδομένα μνήμης
    output [31:0] dWriteData, // Δεδομένα προς εγγραφή στη μνήμη δεδομένων
    output reg MemRead, //Σήμα ελέγχου που υποδεικνύει ανάγνωση μνήμης
    output reg MemWrite, //Σήμα ελέγχου που υποδεικνύει εγγραφή στη μνήμη
    output [31:0] WriteBackData); //Δεδομένα που εγγράφονται σε καταχωρητές (για αποσφαλμάτωση)

//PARAMETERS -----------------------------------------------------------------------------------
    parameter [31:0] INITIAL_PC = 32'h00400000; 
        //Parameters of FSM states - one-hot αποκωδικοποιητης
    parameter [4:0] IF = 5'b00001;
    parameter [4:0] ID = 5'b00010;
    parameter [4:0] EX = 5'b00100;
    parameter [4:0] MEM = 5'b01000;
    parameter [4:0] WB = 5'b10000;
        //Parameters of Instruction Types
    parameter [6:0] OP_I = 7'b0010011; //I-type
    parameter [6:0] OP_LW = 7'b0000011; //LW
    parameter [6:0] OP_SW = 7'b0100011; //SW
    parameter [6:0] OP_BEQ = 7'b1100011; //BEQ
    parameter [6:0] OP_R = 7'b0110011; //R-type
        //Parameters of alu_op -- MUX!!!
    parameter[3:0] ALUOP_AND = 4'b0000;
    parameter[3:0] ALUOP_OR = 4'b0001;
    parameter[3:0] ALUOP_ADD = 4'b0010;
    parameter[3:0] ALUOP_SUB = 4'b0110;
    parameter[3:0] ALUOP_SLT = 4'b0111; //less than
    parameter[3:0] ALUOP_SRL = 4'b1000; //right shift
    parameter[3:0] ALUOP_SLL = 4'b1001; //left shift
    parameter[3:0] ALUOP_SRA = 4'b1010; //right arithmetic shift
    parameter[3:0] ALUOP_XOR = 4'b1101;

    //Instantiations-------------------------------------------------------------------
    //Datapath
    datapath DATAPATH(.PC(PC) ,.instr(instr) ,.dAddress(dAddress) ,.dReadData(dReadData) ,.dWriteData(dWriteData) 
                    ,.clk(clk) ,.rst(rst) ,.ALUCtrl(ALUCtrl) ,.ALUSrc(ALUSrc) ,.WriteBackData(WriteBackData) ,.MemToReg(MemToReg) 
                    ,.PCSrc(PCSrc) ,.loadPC(loadPC) ,.RegWrite(RegWrite) ,.Zero(Zero));
    //RAM & ROM
    //INSTRUCTION_MEMORY rom(.clk(clk) ,.addr(PC[8:0]) ,.dout(instr)); //Instruction Memory
    //DATA_MEMORY ram(.clk(clk) ,.we(we) ,.addr(dAddress[8:0]) ,.din(dWriteData) ,.dout(dReadData)); //Data Memory


//FSM - 5 States---------------------------------------------------------
    reg if_enable;
    reg id_enable;
    reg ex_enable;
    reg mem_enable;
    reg wb_enable;
    reg [4:0] state;
  
    always @(posedge clk) //με το clk αλλάζει
    begin // FSM Logic
        if (rst)
            state <= IF;
        else
            case(state)
                IF: state <= ID;
                ID: state <= EX;
                EX: state <= MEM;
                MEM: state <= WB;
                WB: state <= IF;
                default: state <= IF;
        endcase
    end

    always @* 
    begin // Control Signals
        if_enable = (state == IF);
        id_enable = (state == ID);
        ex_enable = (state == EX);
        mem_enable = (state == MEM);
        wb_enable = (state == WB);
    end


    //ALUCtrl----------------------------------------------------------------------------------------------------------------------
    reg [3:0] ALUCtrl; //4bit
        //instruction type
    wire [6:0] opcode; //7bit
    wire [2:0] funct3; //3bit
    wire [6:0] funct7; //7bit
    
    assign opcode = instr[6:0];
    assign funct3 = instr[14:12];
    assign funct7 = instr[31:25];

    always @*
    begin // ALUCtrl --> alu_op
        case(opcode)
            OP_SW: /*SW*/ ALUCtrl = ALUOP_ADD;  //SW πρόσθεση ALUOP_ADD
            OP_LW: /*LW*/ ALUCtrl = ALUOP_ADD; //LW πρόσθεση ALUOP_ADD
            OP_BEQ: /*BEQ*/ ALUCtrl = ALUOP_SUB; //BEQ αφαίρεση ALUOP_SUB
            default: 
            begin // R-type & I-type  
                case(funct3)
                    3'b000: ALUCtrl = (funct7==7'b0100000 && opcode==OP_R) ? ALUOP_SUB : ALUOP_ADD; 
                        //MUX   //SUB or ADDI/ADD
                    3'b010: ALUCtrl = ALUOP_SLT; //SLTI /SLT
                    3'b100: ALUCtrl = ALUOP_XOR; //XORI /XOR
                    3'b110: ALUCtrl = ALUOP_OR; //ORI /OR
                    3'b111: ALUCtrl = ALUOP_AND; //ANDI /AND
                    //SHAMT
                    3'b001: ALUCtrl = ALUOP_SLL; //SLLI /SLL
                    3'b101: //MUX   //funct7 --> SRLI-0000000 -- SRAI-0100000
                        ALUCtrl = (funct7 == 7'b0000000) ? ALUOP_SRL : ALUOP_SRA; // SRLI/SRL or SRAI/SRA             
                endcase
            end
        endcase
    end

//AluSrc ---------------------------------------------------------------
    reg ALUSrc; //1bit

    //Άμεσα δεδομένα απαιτούνται μόνο για τις εντολές 'load','store' και 'ALU Immediate'. 
    always @*
    begin // ALUSrc
        case(opcode)
            OP_I: ALUSrc = 1'b1;//ALU Immediate - I type
            OP_LW: ALUSrc = 1'b1;//LW - load
            OP_SW: ALUSrc = 1'b1;//SW - store
            default: ALUSrc = 1'b0;
        endcase
    end


//------MEM του FSM------------------------------------------------------------------
    // MemRead-MemWrite ---> ram.we

    always @*
    begin 
        if (mem_enable) //FOR MEM STATE
        begin
            case (opcode)
                OP_LW: begin //LW - load
                    MemRead = 1'b1; MemWrite = 1'b0;
                end
                OP_SW: begin //SW - store
                    MemRead = 1'b0; MemWrite = 1'b1;
                end
                default: begin
                    MemRead = 1'b0; MemWrite = 1'b0;
                end
            endcase
        end
        else begin //MemWrite, MemRead τίθενται µόνο κατά τη διάρκεια του σταδίου 'MEM' της µηχανής FSM.
            MemRead=1'b0; MemWrite=1'b0;
        end
    end


//---------WB του FSM---------------------------------------------------------------------
    reg RegWrite; //1bit    
    
    always @*
    begin //RegWrite(WB state)
        RegWrite = (wb_enable && ((opcode==OP_I) || (opcode==OP_LW) || (opcode==OP_R))) ? 1'b1 : 1'b0; //RegWrite 1 μόνο όταν state == WB
    end
    
    
    reg MemToReg; //1bit
    
    always @*
    begin //MemToReg
        MemToReg = (opcode==OP_LW)  ? 1'b1 : 1'b0; //δεν εξαρτάται απο το state, μόνο από την εντολή load --> LW
    end


    reg loadPC; //1bit 
    
    always @*
    begin // loadPC
        loadPC = (wb_enable) ? 1'b1 : 1'b0; //φορτώνει νέα τιμή PC πριν την IF (στην WB)
    end


    wire Branch; //1bit --> OP_BEQ από Σχήμα 6
    wire Zero; //1bit   (alu.zero)
    reg PCSrc; //1bit

    assign Branch = (opcode==OP_BEQ); //Branch ισχύει μόνο για opcode == OP_BEQ (τότε, true, παίρνει την τιμή 1)

    always @*
    begin
        if ((Branch) && (Zero==1'b1))//BEQ εντολή  (&&-->λογικό και) 
            PCSrc = 1'b1;
        else
            PCSrc = 1'b0;
    end
    /*Το σήµα 'PCSrc' πρέπει να τίθεται σε '1' όταν υπάρχουν οι ακόλουθες συνθήκες: 
        (1) η τρέχουσα εντολή είναι μια λειτουργία "BEQ" και 
        (2) το Zero είναι ίσο με '1'*/
endmodule

HW_Solution/HW5/multicycle_tb.v
`timescale 1ns/1ns
`include "multicycle.v"
`include "rom.v"
`include "ram.v"
//`include "rom_bytes.data"

module multicycle_tb;
    //Inputs
    reg clk, rst;
    wire [31:0] instr;
    wire [31:0] dReadData;

    //Outputs
    wire [31:0] PC;
    wire [31:0] dAddress;
    wire [31:0] dWriteData;
    wire MemRead, MemWrite;
    wire [31:0] WriteBackData;

    //Instantiation of multicycle (top) module
    multicycle TB(.clk(clk) ,.rst(rst) ,.instr(instr) ,.dReadData(dReadData) ,.PC(PC) ,
    .dAddress(dAddress) ,.dWriteData(dWriteData) ,.MemRead(MemRead) ,.MemWrite(MemWrite) ,.WriteBackData(WriteBackData));
    
    //RAM & ROM
    INSTRUCTION_MEMORY rom(.clk(clk) ,.addr(PC[8:0]) ,.dout(instr)); //Instruction Memory
    DATA_MEMORY ram(.clk(clk) ,.we(MemWrite) ,.addr(dAddress[8:0]) ,.din(dWriteData) ,.dout(dReadData)); //Data Memory
        //we = MemWrite ---> μόνο όταν γράφω στην μνήμη το we = 1 .


    initial
    begin
        clk = 1'b1;
    end
    always
    begin
        #10 clk = ~clk; //παλμός ρολογιού
    end

    initial begin 
        $dumpfile("multicycle_tb.vcd"); //value change dump
        $dumpvars(0, multicycle_tb);

        rst = 1'b1;
        #10;
        #10 rst = 1'b0; //dReadData = 32'b0;
        #10;

        #12800 $finish;
    end
endmodule

/*Χρησιμοποιήστε τα αρχεία μνημών που σας δίνονται για τη μνήμη εντολών και για τη μνήμη
δεδομένων, καθώς και τo αρχείo με την αρχικοποίηση των εντολών (.data) και εκτελέστε
προσομοιώσεις.
*/

HW_Solution/HW5/multicycle_tb.vcd
$date
	Sun Jan 21 19:55:25 2024
$end
$version
	Icarus Verilog
$end
$timescale
	1ns
$end
$scope module multicycle_tb $end
$var wire 1 ! MemRead $end
$var wire 1 " MemWrite $end
$var wire 32 # PC [31:0] $end
$var wire 32 $ WriteBackData [31:0] $end
$var wire 32 % dAddress [31:0] $end
$var wire 32 & dReadData [31:0] $end
$var wire 32 ' dWriteData [31:0] $end
$var wire 32 ( instr [31:0] $end
$var reg 1 ) clk $end
$var reg 1 * rst $end
$scope module TB $end
$var wire 1 + Branch $end
$var wire 32 , PC [31:0] $end
$var wire 32 - WriteBackData [31:0] $end
$var wire 1 . Zero $end
$var wire 1 / clk $end
$var wire 32 0 dAddress [31:0] $end
$var wire 32 1 dReadData [31:0] $end
$var wire 32 2 dWriteData [31:0] $end
$var wire 3 3 funct3 [2:0] $end
$var wire 7 4 funct7 [6:0] $end
$var wire 32 5 instr [31:0] $end
$var wire 7 6 opcode [6:0] $end
$var wire 1 7 rst $end
$var reg 4 8 ALUCtrl [3:0] $end
$var reg 1 9 ALUSrc $end
$var reg 1 : MemRead $end
$var reg 1 ; MemToReg $end
$var reg 1 < MemWrite $end
$var reg 1 = PCSrc $end
$var reg 1 > RegWrite $end
$var reg 1 ? ex_enable $end
$var reg 1 @ id_enable $end
$var reg 1 A if_enable $end
$var reg 1 B loadPC $end
$var reg 1 C mem_enable $end
$var reg 5 D state [4:0] $end
$var reg 1 E wb_enable $end
$scope module DATAPATH $end
$var wire 4 F ALUCtrl [3:0] $end
$var wire 1 G ALUSrc $end
$var wire 1 H MemToReg $end
$var wire 1 I PCSrc $end
$var wire 1 J RegWrite $end
$var wire 32 K WriteBackData [31:0] $end
$var wire 1 . Zero $end
$var wire 32 L alu_result [31:0] $end
$var wire 32 M branch_offset [31:0] $end
$var wire 1 / clk $end
$var wire 32 N dAddress [31:0] $end
$var wire 32 O dReadData [31:0] $end
$var wire 32 P dWriteData [31:0] $end
$var wire 32 Q instr [31:0] $end
$var wire 1 R loadPC $end
$var wire 7 S opcode [6:0] $end
$var wire 32 T readData1 [31:0] $end
$var wire 32 U readData2 [31:0] $end
$var wire 1 7 rst $end
$var reg 32 V PC [31:0] $end
$var reg 32 W alu_op2 [31:0] $end
$var reg 32 X immB [31:0] $end
$var reg 32 Y immI [31:0] $end
$var reg 32 Z immLW [31:0] $end
$var reg 32 [ immS [31:0] $end
$var reg 32 \ writeData [31:0] $end
$scope module datapath__REGFILE $end
$var wire 1 / clk $end
$var wire 5 ] readReg1 [4:0] $end
$var wire 5 ^ readReg2 [4:0] $end
$var wire 1 J write $end
$var wire 32 _ writeData [31:0] $end
$var wire 5 ` writeReg [4:0] $end
$var integer 32 a i [31:0] $end
$var reg 32 b readData1 [31:0] $end
$var reg 32 c readData2 [31:0] $end
$upscope $end
$scope module datapath_ALU $end
$var wire 4 d alu_op [3:0] $end
$var wire 32 e op1 [31:0] $end
$var wire 32 f op2 [31:0] $end
$var reg 32 g result [31:0] $end
$var reg 1 h zero $end
$upscope $end
$upscope $end
$upscope $end
$scope module rom $end
$var wire 9 i addr [8:0] $end
$var wire 1 / clk $end
$var reg 32 j dout [31:0] $end
$upscope $end
$scope module ram $end
$var wire 9 k addr [8:0] $end
$var wire 1 / clk $end
$var wire 32 l din [31:0] $end
$var wire 1 " we $end
$var reg 32 m dout [31:0] $end
$upscope $end
$upscope $end
$enddefinitions $end
#0
$dumpvars
bx m
bx l
bx k
bx j
b0 i
xh
bx g
bx f
bx e
bx d
bx c
bx b
b100000 a
bx `
bx _
bx ^
bx ]
bx \
bx [
bx Z
bx Y
bx X
bx W
b10000000000000000000000 V
bx U
bx T
bx S
0R
bx Q
bx P
bx O
bx N
bx0 M
bx L
bx K
0J
0I
xH
0G
bx F
0E
b1 D
0C
0B
1A
0@
0?
0>
0=
0<
x;
0:
09
bx 8
17
bx 6
bx 5
bx 4
bx 3
bx 2
bx 1
bx 0
1/
x.
bx -
b10000000000000000000000 ,
x+
1*
1)
bx (
bx '
bx &
bx %
bx $
b10000000000000000000000 #
0"
0!
$end
#10
0)
0/
#20
b100 W
b100 f
b100 Y
19
1G
0;
0H
b10 8
b10 F
b10 d
b10011 S
b1 `
b100 ^
b0 ]
b0 4
b0 3
0+
b10011 6
1@
0A
b10000000000000010010011 j
b10000000000000010010011 (
b10000000000000010010011 5
b10000000000000010010011 Q
b10 D
0*
07
1)
1/
#30
0)
0/
#40
b100 k
b100 \
b100 _
b100 $
b100 -
b100 K
0h
0.
b100 g
b100 L
b100 %
b100 0
b100 N
1?
0@
b0 c
b0 U
b0 '
b0 2
b0 P
b0 l
b0 b
b0 T
b0 e
b100 D
1)
1/
#50
0)
0/
#60
1C
0?
b1000 D
1)
1/
#70
0)
0/
#80
1B
1R
1>
1J
1E
0C
b10000 D
1)
1/
#90
0)
0/
#100
0B
0R
0>
0J
0E
1A
b1 D
b100 i
b10000000000000000000100 V
b10000000000000000000100 #
b10000000000000000000100 ,
1)
1/
#110
0)
0/
#120
b1 k
b1 \
b1 _
b1 $
b1 -
b1 K
b1 g
b1 L
b1 %
b1 0
b1 N
b1 W
b1 f
1@
0A
b10 `
b1 ^
b1 Y
b10 D
b100000000000100010011 j
b100000000000100010011 (
b100000000000100010011 5
b100000000000100010011 Q
1)
1/
#130
0)
0/
#140
1?
0@
b100 D
b100 c
b100 U
b100 '
b100 2
b100 P
b100 l
1)
1/
#150
0)
0/
#160
1C
0?
b1000 D
1)
1/
#170
0)
0/
#180
1B
1R
1>
1J
1E
0C
b10000 D
1)
1/
#190
0)
0/
#200
0B
0R
0>
0J
0E
1A
b1 D
b1000 i
b10000000000000000001000 V
b10000000000000000001000 #
b10000000000000000001000 ,
1)
1/
#210
0)
0/
#220
b11 k
b11 \
b11 _
b11 $
b11 -
b11 K
b11 g
b11 L
b11 %
b11 0
b11 N
b11 W
b11 f
b11 `
b11 ^
b11 Y
1@
0A
b1100000000000110010011 j
b1100000000000110010011 (
b1100000000000110010011 5
b1100000000000110010011 Q
b10 D
1)
1/
#230
0)
0/
#240
1?
0@
b0 c
b0 U
b0 '
b0 2
b0 P
b0 l
b100 D
1)
1/
#250
0)
0/
#260
1C
0?
b1000 D
1)
1/
#270
0)
0/
#280
1B
1R
1>
1J
1E
0C
b10000 D
1)
1/
#290
0)
0/
#300
0B
0R
0>
0J
0E
1A
b1 D
b11 c
b11 U
b11 '
b11 2
b11 P
b11 l
b1100 i
b10000000000000000001100 V
b10000000000000000001100 #
b10000000000000000001100 ,
1)
1/
#310
0)
0/
#320
b111 k
b111 \
b111 _
b111 $
b111 -
b111 K
b111 g
b111 L
b111 %
b111 0
b111 N
b111 W
b111 f
1@
0A
b100 `
b111 ^
b111 Y
b10 D
b11100000000001000010011 j
b11100000000001000010011 (
b11100000000001000010011 5
b11100000000001000010011 Q
1)
1/
#330
0)
0/
#340
1?
0@
b100 D
b0 c
b0 U
b0 '
b0 2
b0 P
b0 l
1)
1/
#350
0)
0/
#360
1C
0?
b1000 D
1)
1/
#370
0)
0/
#380
1B
1R
1>
1J
1E
0C
b10000 D
1)
1/
#390
0)
0/
#400
0B
0R
0>
0J
0E
1A
b1 D
b10000 i
b10000000000000000010000 V
b10000000000000000010000 #
b10000000000000000010000 ,
1)
1/
#410
0)
0/
#420
b111111110 k
b11111111111111111111111111111110 \
b11111111111111111111111111111110 _
b11111111111111111111111111111110 $
b11111111111111111111111111111110 -
b11111111111111111111111111111110 K
b11111111111111111111111111111110 g
b11111111111111111111111111111110 L
b11111111111111111111111111111110 %
b11111111111111111111111111111110 0
b11111111111111111111111111111110 N
b11111111111111111111111111111110 W
b11111111111111111111111111111110 f
b101 `
b11110 ^
b11111111111111111111111111111110 Y
b1111111 4
1@
0A
b11111111111000000000001010010011 j
b11111111111000000000001010010011 (
b11111111111000000000001010010011 5
b11111111111000000000001010010011 Q
b10 D
1)
1/
#430
0)
0/
#440
1?
0@
b100 D
1)
1/
#450
0)
0/
#460
1C
0?
b1000 D
1)
1/
#470
0)
0/
#480
1B
1R
1>
1J
1E
0C
b10000 D
1)
1/
#490
0)
0/
#500
0B
0R
0>
0J
0E
1A
b1 D
b10100 i
b10000000000000000010100 V
b10000000000000000010100 #
b10000000000000000010100 ,
1)
1/
#510
0)
0/
#520
09
0G
1@
0A
b110011 S
b110 `
b11 ^
b11 ]
b11 Y
b0 4
b110011 6
b10 D
b1100011000001100110011 j
b1100011000001100110011 (
b1100011000001100110011 5
b1100011000001100110011 Q
1)
1/
#530
0)
0/
#540
b1 k
b1 \
b1 _
b1 $
b1 -
b1 K
1?
0@
b1 g
b1 L
b1 %
b1 0
b1 N
b100 D
b11 c
b11 U
b11 '
b11 2
b11 P
b11 l
b11 b
b11 T
b11 e
1)
1/
#550
0)
0/
#560
1C
0?
b1000 D
1)
1/
#570
0)
0/
#580
1B
1R
1>
1J
1E
0C
b10000 D
1)
1/
#590
0)
0/
#600
0B
0R
0>
0J
0E
1A
b1 D
b11000 i
b10000000000000000011000 V
b10000000000000000011000 #
b10000000000000000011000 ,
1)
1/
#610
0)
0/
#620
b101 k
b101 \
b101 _
b101 $
b101 -
b101 K
b101 g
b101 L
b101 %
b101 0
b101 N
b110 8
b110 F
b110 d
b111 `
b101 ^
b110 ]
b100000 4
1@
0A
b1000000010100110000001110110011 j
b1000000010100110000001110110011 (
b1000000010100110000001110110011 5
b1000000010100110000001110110011 Q
b10 D
1)
1/
#630
0)
0/
#640
b11 k
b11 \
b11 _
b11 $
b11 -
b11 K
b11 g
b11 L
b11 %
b11 0
b11 N
1?
0@
b11111111111111111111111111111110 c
b11111111111111111111111111111110 U
b11111111111111111111111111111110 '
b11111111111111111111111111111110 2
b11111111111111111111111111111110 P
b11111111111111111111111111111110 l
b1 b
b1 T
b1 e
b100 D
1)
1/
#650
0)
0/
#660
1C
0?
b1000 D
1)
1/
#670
0)
0/
#680
1B
1R
1>
1J
1E
0C
b10000 D
1)
1/
#690
0)
0/
#700
0B
0R
0>
0J
0E
1A
b1 D
b11100 i
b10000000000000000011100 V
b10000000000000000011100 #
b10000000000000000011100 ,
1)
1/
#710
0)
0/
#720
b0 k
b1000000000000000000000000000000 \
b1000000000000000000000000000000 _
b1000000000000000000000000000000 $
b1000000000000000000000000000000 -
b1000000000000000000000000000000 K
b1000000000000000000000000000000 g
b1000000000000000000000000000000 L
b1000000000000000000000000000000 %
b1000000000000000000000000000000 0
b1000000000000000000000000000000 N
b1001 8
b1001 F
b1001 d
1@
0A
b1000 `
b10 ^
b11 ]
b0 4
b1 3
b10 D
b1000011001010000110011 j
b1000011001010000110011 (
b1000011001010000110011 5
b1000011001010000110011 Q
1)
1/
#730
0)
0/
#740
b11000000000000000000000000000000 \
b11000000000000000000000000000000 _
b11000000000000000000000000000000 $
b11000000000000000000000000000000 -
b11000000000000000000000000000000 K
1?
0@
b11000000000000000000000000000000 g
b11000000000000000000000000000000 L
b11000000000000000000000000000000 %
b11000000000000000000000000000000 0
b11000000000000000000000000000000 N
b100 D
b1 c
b1 U
b1 '
b1 2
b1 P
b1 l
b11 b
b11 T
b11 e
1)
1/
#750
0)
0/
